{
  "非ST段抬高型急性冠脉综合征": [
    "NSTE-ACS",
    "非ST段抬高型急性冠脉综合征"
  ],
  "替罗非班": [
    "GPI",
    "替罗非班",
    "Tirofiban"
  ],
  "肾小球滤过率": [
    "GFR",
    "肾小球滤过率"
  ],
  "急性缺血性卒中": [
    "急性脑梗死",
    "急性缺血性卒中",
    "缺血性卒中"
  ],
  "进展性卒中": [
    "进展性卒中"
  ],
  "小动脉闭塞型": [
    "小动脉闭塞型"
  ],
  "阿司匹林": [
    "阿司匹林"
  ],
  "静脉溶栓": [
    "静脉溶栓",
    "溶栓"
  ],
  "阿替普酶": [
    "阿替普酶"
  ],
  "症状性颅内出血": [
    "症状性颅内出血"
  ],
  "神经功能缺损症状": [
    "神经功能缺损症状"
  ],
  "早期神经功能恶化": [
    "早期神经功能恶化"
  ],
  "神经功能结局": [
    "神经功能结局"
  ],
  "mRS评分": [
    "mRS评分"
  ],
  "死亡率": [
    "死亡率"
  ],
  "溶栓时间窗": [
    "溶栓时间窗"
  ],
  "血栓性卒中": [
    "血栓性卒中"
  ]
}